Workbook

Sheet Summary
A1: DOFT x ProMarcom
A2: Diwali Pop-Up Kiosk - Programme Cost Summary - 14 malls, 8 ft x 8 ft
A3: Assumptions (edit gold cells)
A4: No. of kiosks / malls | C4: 14
A5: Operating window (weeks) | C5: 6
A6: Operating days (per kiosk) | C6: 45
A7: Management fee | C7: =0.10
A8: GST | C8: =0.18
A10: Cost Head | B10: Ref | C10: Per kiosk (Rs) | D10: Programme (Rs) | E10: Notes
A11: A. Kiosk setup & build | B11: Setup Cost | C11: ='Setup Cost'!F17 | D11: ='Setup Cost'!F18 | E11: Design, fabrication, install, dismantle
A12: B. Manpower | B12: Manpower Cost | C12: ='Manpower Cost'!G11+'Manpower Cost'!G16 | D12: ='Manpower Cost'!G17 | E12: Sales, billing, supervision, city mgr
A13: C. Other elements | B13: Other Elements | C13: ='Other Elements'!D15 | D13: ='Other Elements'!D16 | E13: Logistics, warehouse, insurance, ops
A14: D. Location / mall space | B14: Location Charges | C14: n/a | D14: ='Location Charges'!G19 | E14: 3-day rate card, ex-GST; 6-wk TBD
A15: Programme sub-total (ex-GST) | D15: =SUM(D11:D14)
A16: Management fee | B16: =C7 | D16: =D15*$C$7 | E16: % of programme sub-total
A17: Sub-total incl. management fee | D17: =D15+D16
A18: GST | B18: =C8 | D18: =D17*$C$8 | E18: 18% on sub-total incl. fee
A19: GRAND TOTAL (incl. GST) | D19: =D17+D18
A21: Per-kiosk average (incl. GST) | D21: =D19/$C$4
A23: Basis & notes:
A24: - Figures sourced from the execution-agency ops sheet (build + manpower + logistics + insurance) and the mall activation rate card.
A25: - Location / mall space (D) is a 3-day (Fri-Sun) rate card, ex-GST; the 6-week festive licence, CAM, electricity and deposits are to be negotiated per mall (blank).
A26: - Management fee modelled at 10% of programme sub-total (the source sheet contained an apparent calculation error on this line).
A27: - Billing hardware/software and security deposits left blank pending confirmation.
A28: - All rates indicative placeholders; confirm against vendor, mall and statutory quotes before commercial submission.

Sheet Cities List
A1: Cities & Malls - Revised List (14)
A2: Per the client's revised preferred-mall list. Footfall & activity location per the mall rate card.
A4: # | B4: City | C4: Preferred Mall | D4: Location / Zone | E4: Region | F4: Weekend Footfall
A5: 1 | B5: Delhi | C5: Select Citywalk | D5: Saket | E5: North | F5: 50-60k
A6: 2 | B6: Noida | C6: DLF Mall of India | D6: Noida | E6: North | F6: 50-60k
A7: 3 | B7: Gurgaon | C7: Ambience Mall | D7: Gurgaon | E7: North | F7: 50-60k
A8: 4 | B8: Chandigarh | C8: Elante Mall | D8: Industrial Area | E8: North | F8: 50-60k
A9: 5 | B9: Lucknow | C9: Lulu Mall | D9: Hariharpur | E9: North | F9: 40-45k
A10: 6 | B10: Mumbai (BKC) | C10: Jio World Mall | D10: BKC | E10: West | F10: 50-60k
A11: 7 | B11: Mumbai (Lower Parel) | C11: Phoenix Palladium | D11: Lower Parel | E11: West | F11: 40-45k
A12: 8 | B12: Ahmedabad | C12: Phoenix / Palladium | D12: Thaltej | E12: West | F12: 40-45k
A13: 9 | B13: Nagpur | C13: VR Mall | D13: Untkhana | E13: West | F13: 30-35k
A14: 10 | B14: Kolkata | C14: South City Mall | D14: Jadavpur | E14: East | F14: 50-60k
A15: 11 | B15: Chennai | C15: Phoenix Marketcity | D15: Velachery | E15: South | F15: 50-60k
A16: 12 | B16: Bengaluru | C16: Phoenix Marketcity | D16: Whitefield | E16: South | F16: 50-60k
... A18: 14 | B18: Kochi | C18: Lulu International Mall | D18: Ernakulam | E18: South | F18: 50-60k
B19: Total locations | E19: =COUNTA(B5:B18)

Sheet Setup Cost
A1: Setup Cost - Kiosk Design, Build & Install
A2: 8 ft x 8 ft kiosk. Headline build cost per execution-agency quote (Rs 3,50,000/kiosk); component split below is indicative.
A4: # | B4: Component | C4: Specification / Scope | D4: Unit | E4: Qty | F4: Amount / kiosk (Rs) | G4: Remarks
A5: 1 | B5: Structure & framework | C5: MS/GI frame, base platform, carcass | D5: Lot | E5: 1 | F5: 55000 | G5: Core structure
A6: 2 | B6: Body cladding & finish | C6: Warm-white PU-lacquer panels, fluted detailing | D6: Lot | E6: 1 | F6: 60000 | G6: Body finish
A7: 3 | B7: Counters | C7: Black-stone tops, lockable storage bodies | D7: Lot | E7: 1 | F7: 45000 | G7: Display + billing counters
A8: 4 | B8: Brass gallery shelving & display | C8: Backlit floating shelves, brass fronts | D8: Lot | E8: 1 | F8: 45000 | G8: Merchandising
A9: 5 | B9: Backlit brand signage | C9: Illuminated seal wall, fascia, backlit counter fronts | D9: Lot | E9: 1 | F9: 40000 | G9: Hero signage
A10: 6 | B10: Lighting | C10: Warm LED strips, drivers, downlights | D10: Lot | E10: 1 | F10: 25000 | G10: 3000K
A11: 7 | B11: Electrical | C11: Concealed wiring, DB/MCB, sockets | D11: Lot | E11: 1 | F11: 15000 | G11: Single power drop
A12: 8 | B12: Flooring & platform | C12: Deck finish, warm-LED perimeter | D12: Lot | E12: 1 | F12: 18000
A13: 9 | B13: Digital brand screen + stand | C13: Screen for brand film / catalogue | D13: Nos | E13: 1 | F13: 12000
A14: 10 | B14: Furniture | C14: Consultation table + 4 chairs | D14: Set | E14: 1 | F14: 15000
A15: 11 | B15: Graphics, styling & props | C15: Vinyls, Diwali dressing | D15: Lot | E15: 1 | F15: 8000
A16: 12 | B16: Transport, install & dismantle | C16: Delivery, on-site setup, dismantle | D16: Lot | E16: 1 | F16: 12000 | G16: 3-day buffer before go-live
B17: Per-kiosk setup total | F17: =SUM(F5:F16)
B18: Programme setup (x 14 kiosks) | E18: =Summary!$C$4 | F18: =F17*Summary!$C$4

Sheet Manpower Cost
A1: Manpower Cost
A2: Per-kiosk deployment for the operating window; city-level roles added per city. Rates per execution-agency sheet.
A4: # | B4: Role | C4: Basis | D4: Count | E4: Rate (Rs) | F4: Days / Units | G4: Amount / kiosk (Rs) | H4: Remarks
A5: 1 | B5: Sales Executive | C5: Daily | D5: 5 | E5: 1600 | F5: 45 | G5: =D5*E5*F5 | H5: 2 also handle billing; female, 22-25, fluent English
A6: 2 | B6: Helper | C6: Daily | D6: 2 | E6: 1200 | F6: 42 | G6: =D6*E6*F6 | H6: Housekeeping, stock handling, refill
A7: 3 | B7: Supervisor | C7: Daily | D7: 1 | E7: 1800 | F7: 42 | G7: =D7*E7*F7 | H7: Day-to-day kiosk operations
A8: 4 | B8: Training Support | C8: Lump | D8: 1 | E8: 15000 | F8: 1 | G8: =D8*E8*F8 | H8: 1-day product & sales training
A9: 5 | B9: Store Operations & Cash | C9: Lump | D9: 1 | E9: 10000 | F9: 1 | G9: =D9*E9*F9 | H9: Open/close, billing, cash, reconciliation
A10: 6 | B10: Reporting | C10: Daily | D10: 1 | E10: 150 | F10: 45 | G10: =D10*E10*F10 | H10: Sales/footfall/stock/attendance reports
B11: Per-kiosk manpower subtotal | G11: =SUM(G5:G10)
B13: City-level roles
A14: 1 | B14: City Manager | C14: Monthly | D14: 1 | E14: 50000 | F14: 1 | G14: =D14*E14*F14 | H14: 1 per city (cities with >2 kiosks)
A15: 2 | B15: Trained Backup Bench | C15: Lump | D15: 1 | E15: 20000 | F15: 1 | G15: =D15*E15*F15 | H15: Replacement cover; per city
B16: Per-city subtotal | G16: =SUM(G14:G15)
B17: Programme manpower (per-kiosk + per-city) x 14 | G17: =(G11+G16)*Summary!$C$4

Sheet Location Charges
A1: Location Charges - Mall Space
A2: Mall activation rate card (3-day Fri-Sun, ex-GST). 6-week festive licence to be negotiated (left blank). GST 18% extra.
A4: # | B4: City | C4: Mall | D4: Activity Location | E4: Weekend Footfall | F4: Size | G4: 3-day rate (Rs, ex-GST) | H4: 6-wk licence (Rs) | I4: Remarks
A5: 1 | B5: Delhi NCR | C5: Select City Walk | D5: Mac Atrium | E5: 50-60k | F5: 8x8ft | G5: 840000 | I5: Incl. Police & MCD permission
A6: 2 | B6: Noida | C6: DLF Mall of India | D6: Main Atrium | E6: 50-60k | F6: 8x8ft | G6: 728000 | I6: DLF do's & don'ts apply
A7: 3 | B7: Gurgaon | C7: Ambience Mall | D7: Uniqlo Atrium | E7: 50-60k | F7: 8x8ft | G7: 840000 | I7: Incl. Police & MCG permission
A8: 4 | B8: Chandigarh | C8: Elante Mall | D8: Atrium | E8: 50-60k | F8: 8x8ft | G8: 728000
A9: 5 | B9: Lucknow | C9: Lulu Mall | D9: Atrium | E9: 40-45k | F9: 8x8ft | G9: 532000
A10: 6 | B10: Mumbai (BKC) | C10: Jio World Drive | D10: GF Atrium | E10: 50-60k | F10: 8x8ft | G10: 784000 | I10: Incl. Police & BMC permission
A11: 7 | B11: Mumbai (Lower Parel) | C11: Phoenix Palladium | D11: Courtyard (open) | E11: 40-45k | F11: 8x8ft | G11: 840000 | I11: Incl. Police & BMC permission
A12: 8 | B12: Ahmedabad | C12: Palladium Ahmedabad | D12: Atrium | E12: 40-45k | F12: 8x8ft | G12: 784000
A13: 9 | B13: Nagpur | C13: VR Mall | D13: Atrium | E13: 30-35k | F13: 8x8ft | G13: 308000
A14: 10 | B14: Kolkata | C14: South City Mall | D14: Main Atrium | E14: 50-60k | F14: 8x8ft | G14: 336000
A15: 11 | B15: Chennai | C15: Phoenix Market City | D15: Atrium | E15: 50-60k | F15: 8x8ft | G15: 700000
A16: 12 | B16: Bengaluru | C16: Phoenix Market City | D16: Main Atrium | E16: 50-60k | F16: 8x8ft | G16: 560000
A17: 13 | B17: Hyderabad | C17: Sarath City Capital | D17: Main Atrium | E17: 50-60k | F17: 8x8ft | G17: 532000 | I17: Inorbit alt: Rs 5,60,000
A18: 14 | B18: Kochi | C18: Lulu International Mall | D18: Main Atrium | E18: 50-60k | F18: 8x8ft | G18: 840000
C19: Total mall space (3-day basis, ex-GST) | G19: =SUM(G5:G18)
A21: Notes:
A22: - Rates are 3-day (Fri-Sun) activation rates, ex-GST, per the mall rate card; non-festive - festive rates may vary.
A23: - 6-week festive-season licence, CAM, electricity above 3-4 KVA and security deposits to be negotiated per mall (left blank).
A24: - Booking against 100% advance; rates valid 15 days; PPL/IPRS and special permissions extra.

Sheet Other Elements
A1: Other Elements
A2: Logistics, insurance, operations and pass-through items (per kiosk / season). Hardware & software left blank pending confirmation.
A4: # | B4: Element | C4: Specification / Scope | D4: Amount / kiosk (Rs) | E4: Basis | F4: Remarks
A5: 1 | B5: Logistics | C5: Stock pickup (Ghaziabad WH), first fill, replenishment, return of unsold | D5: 25000 | E5: Per season
A6: 2 | B6: Warehouse | C6: Seasonal storage / stockroom | D6: 15000 | E6: Per season
A7: 3 | B7: Insurance - Fire | C7: Mall fire insurance | D7: 10000 | E7: Per season
A8: 4 | B8: Insurance - Transport | C8: Stock in transit | D8: 12000 | E8: Per season
A9: 5 | B9: Extended Trading | C9: Extended ops in select cities (Christmas & New Year) | D9: 20000 | E9: Select only
A10: 6 | B10: Dismantle & Stock Return | C10: Dismantling, fixture removal, unsold-stock return | D10: 10000 | E10: Post-season
A11: 7 | B11: Final Reconciliation | C11: Commercial reconciliation & season review | D11: 0 | E11: Project close
A12: 8 | B12: Billing Hardware | C12: EDC / card machine, thermal printer, tablet, stand | E12: Per kiosk | F12: To be confirmed (may be provided by Doft)
A13: 9 | B13: Billing Software | C13: POS / billing software licence | E13: Per kiosk | F13: To be discussed
A14: 10 | B14: Security Deposit (refundable) | C14: Mall / statutory deposits | E14: Per mall | F14: To be confirmed; refundable
B15: Per-kiosk other subtotal | D15: =SUM(D5:D14)
B16: Programme other (x 14 kiosks) | D16: =D15*Summary!$C$4
