Workbook

Sheet 1. README & Assumptions
A1: Doft Candles — Diwali Pop-Up Retail Operations
A2: ProMarcom Inc. | Operations & Costing Workbook | Seasons 2026 / 2027 / 2028
A4: PURPOSE
A5: This workbook is the operational and commercial toolkit for managing Doft Candles' seasonal Diwali pop-up kiosks. It contains the staffing model, cost/budget build-up, project timeline, and all daily-reporting, compliance and tracking templates required by the client brief.
A7: HOW TO USE
A8: Gold cells | B8: Inputs you edit — rates, counts, dates, actuals.
A9: White cells | B9: Formula-driven — do not overwrite; they recalculate automatically.
A10: Green cells | B10: Roll-up / summary totals.
A12: GLOBAL ASSUMPTIONS (edit these — they drive every other sheet)
A14: Number of cities / regions | B14: 3 | C14: Brief: multi-city. Model default — edit as awarded.
A15: Pop-ups per region | B15: 3 | C15: Brief: 2–4 per region. Mid-point used.
A16: Total pop-ups (calc) | B16: =B14*B15 | C16: Cities × pop-ups per region.
A17: Operational duration (weeks) | B17: 4 | C17: Brief: 3–5 weeks before Diwali.
A18: Setup / fabrication (days) | B18: 5 | C18: Kiosk install + fit-out before go-live.
A19: Training window (days before go-live) | B19: 14 | C19: Brief: training 10–21 days prior.
A20: Staff per pop-up | B20: 12 | C20: Fixed by brief (see Staffing Plan tab).
A21: Operating days per week | B21: 7 | C21: Mall hours, all days.
A22: Store hours per day | B22: 11 | C22: Typical mall trading hours.
A23: Statutory load on wages (PF+ESI+etc.) | B23: 0.13 | C23: ~13% employer statutory contribution.
A24: Contractor management margin | B24: 0.15 | C24: Applied on total direct cost.
A25: GST on contractor invoice | B25: 0.18 | C25: Output GST, 18%.
A26: Currency | B26: INR (₹) | C26: All figures in Indian Rupees.
A28: DISCLAIMER
A29: All pay rates and cost figures are realistic planning placeholders, not quotations. Confirm against actual vendor quotes, mall licence fees, and statutory rates before commercial submission.

Sheet 2. Project Timeline
A1: Project Timeline & Milestones
A2: Per-region rollout — T = kiosk go-live (Diwali season). Weeks shown relative to go-live.
A4: # | B4: Phase / Activity | C4: Owner | D4: Start (T-) | E4: End (T-) | F4: T-6w | G4: T-5w | H4: T-4w | I4: T-3w | J4: T-2w | K4: T-1w
A5: 1 | B5: Contract award & kick-off | C5: Doft + Contractor | D5: T-8w | E5: T-7w
A6: 2 | B6: Mall shortlisting & licence applications | C6: Contractor | D6: T-7w | E6: T-4w
A7: 3 | B7: Kiosk fabrication & fit-out (Doft-approved design) | C7: Contractor | D7: T-3w | E7: T-1w
A8: 4 | B8: Recruitment & background verification | C8: Contractor | D8: T-6w | E8: T-2w
A9: 5 | B9: Doft product & sales training (1 day, 100% attendance) | C9: Doft | D9: T-2w | E9: T-2w
A10: 6 | B10: Statutory registration & staff onboarding/payroll setup | C10: Contractor | D10: T-4w | E10: T-1w
A11: 7 | B11: Stock pickup from Ghaziabad warehouse & first fill | C11: Contractor | D11: T-1w | E11: T-1w
A12: 8 | B12: Store go-live & daily operations (3–5 weeks) | C12: Contractor | D12: T | E12: T+5w
A13: 9 | B13: Daily reporting (sales/footfall/inventory/attendance) | C13: Contractor | D13: T | E13: T+5w
A14: 10 | B14: Replenishment cycles | C14: Contractor | D14: T | E14: T+5w
A15: 11 | B15: Dismantling, fixture return & unsold-stock return | C15: Contractor | D15: T+5w | E15: T+6w
A16: 12 | B16: Final reconciliation & season review | C16: Both | D16: T+6w | E16: T+6w

Sheet 3. Staffing Plan
A1: Staffing Plan — Per Pop-Up
A2: Fixed composition per the brief: 12 personnel per kiosk.
A4: Role | B4: Headcount | C4: Gender / Profile | D4: Key Requirement | E4: Reports To | F4: Employment
A5: Sales Executive | B5: 6 | C5: Female, 22–25 yrs | D5: Fluent conversational English + retail sales experience | E5: Team Leader | F5: ProMarcom payroll
A6: Sales Support Staff | B6: 2 | C6: Any | D6: Merchandising, stock handling, queue mgmt | E6: Team Leader | F6: ProMarcom payroll
A7: Helper | B7: 1 | C7: Any | D7: Housekeeping, material handling | E7: Team Leader | F7: ProMarcom payroll
A8: Cashier | B8: 1 | C8: Any | D8: Experienced with POS/EDC machines | E8: Team Leader | F8: ProMarcom payroll
A9: Driver | B9: 1 | C9: Any | D9: Valid licence; stock transport & runs | E9: Team Leader | F9: ProMarcom payroll
A10: Team Leader / Manager | B10: 1 | C10: Any | D10: Daily operations owner | E10: Contractor Ops Head | F10: Permanent employee of contractor
A11: TOTAL PER POP-UP | B11: =SUM(B5:B10)
A13: Attrition rule (brief): any attrition after training or during operations must be replaced immediately with equally-trained personnel at no additional cost. Maintain a trained bench — see Recruitment Tracker.

Sheet 4. Manpower Cost
A1: Manpower Cost Build-Up
A2: Per pop-up monthly cost × duration, then rolled up to all pop-ups.
A4: Role | B4: Headcount | C4: Monthly CTC (₹) | D4: Statutory Load | E4: Loaded Monthly (₹) | F4: Months | G4: Cost / Pop-up (₹)
A5: Sales Executive | B5: 6 | C5: 22000 | D5: ='1. README & Assumptions'!$B$23 | E5: =C5*(1+D5) | F5: =('1. README & Assumptions'!$B$17+2)/4.33 | G5: =B5*E5*F5
A6: Sales Support Staff | B6: 2 | C6: 16000 | D6: ='1. README & Assumptions'!$B$23 | E6: =C6*(1+D6) | F6: =('1. README & Assumptions'!$B$17+2)/4.33 | G6: =B6*E6*F6
A7: Helper | B7: 1 | C7: 14000 | D7: ='1. README & Assumptions'!$B$23 | E7: =C7*(1+D7) | F7: =('1. README & Assumptions'!$B$17+2)/4.33 | G7: =B7*E7*F7
A8: Cashier | B8: 1 | C8: 20000 | D8: ='1. README & Assumptions'!$B$23 | E8: =C8*(1+D8) | F8: =('1. README & Assumptions'!$B$17+2)/4.33 | G8: =B8*E8*F8
A9: Driver | B9: 1 | C9: 18000 | D9: ='1. README & Assumptions'!$B$23 | E9: =C9*(1+D9) | F9: =('1. README & Assumptions'!$B$17+2)/4.33 | G9: =B9*E9*F9
A10: Team Leader / Manager | B10: 1 | C10: 35000 | D10: ='1. README & Assumptions'!$B$23 | E10: =C10*(1+D10) | F10: =('1. README & Assumptions'!$B$17+2)/4.33 | G10: =B10*E10*F10
A11: TOTAL PER POP-UP | B11: =SUM(B5:B10) | G11: =SUM(G5:G10)
A13: Number of pop-ups | C13: ='1. README & Assumptions'!$B$16
A14: TOTAL MANPOWER COST (all pop-ups) | G14: =G11*C13
A16: Note: 'Months' includes ~2 extra weeks covering setup, training and buffer. Edit CTC (gold) to your actual pay bands.

Sheet 5. Budget Summary
A1: Budget Summary — Full Engagement
A2: All cost heads. Per-pop-up inputs (gold) roll up by total pop-up count.
A4: Cost Head | B4: Basis | C4: Per Pop-up (₹) | D4: Pop-ups | E4: Total (₹) | F4: Notes
A5: Manpower (loaded, full duration) | B5: From Manpower Cost tab | C5: ='4. Manpower Cost'!$G$11 | D5: ='1. README & Assumptions'!$B$16 | E5: =C5*D5 | F5: 6 SE + 2 SS + Helper + Cashier + Driver + TL
A6: Kiosk fabrication, fit-out & signage | B6: Per pop-up | C6: 180000 | D6: ='1. README & Assumptions'!$B$16 | E6: =C6*D6 | F6: On-site fabrication of Doft-approved design
A7: Kiosk transport, install & dismantle | B7: Per pop-up | C7: 45000 | D7: ='1. README & Assumptions'!$B$16 | E7: =C7*D7 | F7: To/from mall, both ways
A8: Mall licence / space fee (if borne) | B8: Per pop-up | C8: 250000 | D8: ='1. README & Assumptions'!$B$16 | E8: =C8*D8 | F8: Confirm per mall — often reimbursed by Doft
A9: Electricity / utilities & access passes | B9: Per pop-up | C9: 25000 | D9: ='1. README & Assumptions'!$B$16 | E9: =C9*D9 | F9: Mall charges for the period
A10: Stockroom (~90 sq ft) rent | B10: Per pop-up | C10: 40000 | D10: ='1. README & Assumptions'!$B$16 | E10: =C10*D10 | F10: Replenishment store
A11: Logistics — Ghaziabad pickup & replenishment | B11: Per pop-up | C11: 60000 | D11: ='1. README & Assumptions'!$B$16 | E11: =C11*D11 | F11: Vehicle, fuel, driver runs
A12: Uniform upkeep (wash/iron/maintain) | B12: Per pop-up | C12: 12000 | D12: ='1. README & Assumptions'!$B$16 | E12: =C12*D12 | F12: Uniforms supplied by Doft; upkeep by contractor
A13: Staff welfare (meals/transport/incentives) | B13: Per pop-up | C13: 55000 | D13: ='1. README & Assumptions'!$B$16 | E13: =C13*D13 | F13: Attendance & sales incentives
A14: Statutory & compliance filing | B14: Per pop-up | C14: 20000 | D14: ='1. README & Assumptions'!$B$16 | E14: =C14*D14 | F14: Licences, registrations, insurance
A15: Training logistics support | B15: Per pop-up | C15: 15000 | D15: ='1. README & Assumptions'!$B$16 | E15: =C15*D15 | F15: Venue coordination, travel for training day
A16: Contingency / attrition replacement buffer | B16: Per pop-up | C16: 30000 | D16: ='1. README & Assumptions'!$B$16 | E16: =C16*D16 | F16: Bench & immediate replacement
A17: DIRECT COST SUBTOTAL | E17: =SUM(E5:E16)
A18: Contractor management margin | D18: ='1. README & Assumptions'!$B$24 | E18: =E17*D18
A19: CONTRACT VALUE (pre-GST) | E19: =E17+E18
A20: GST | D20: ='1. README & Assumptions'!$B$25 | E20: =E19*D20
A21: TOTAL CONTRACT VALUE (incl. GST) | E21: =E19+E20

Sheet 6. Recruitment Tracker
A1: Recruitment & Deployment Tracker
A2: One row per candidate. Track from sourcing through background verification, training and deployment.
A4: Candidate | B4: Role | C4: City | D4: Pop-up ID | E4: Phone | F4: Sourced On | G4: BGV Status | H4: Training Done | I4: Deployment Status | J4: Bench (Y/N) | K4: Remarks
A5: Priya Sharma | B5: Sales Executive | C5: Delhi | D5: DEL-01 | E5: 98xxxxxx01 | F5: 2026-09-20 | G5: Verified | H5: Yes | I5: Deployed | J5: N | K5: Star performer prior season

Sheet 7. Attendance Tracker
A1: Daily Staff Attendance Tracker
A2: Mark P (Present) / A (Absent) / L (Leave) / R (Replaced). One row per staff member.
A4: Staff Name | B4: Role | C4: Pop-up ID | D4: D1 | E4: D2 | F4: D3 | G4: D4 | H4: D5 | I4: D6 | J4: D7 | K4: Present | L4: % Attendance
A5: Priya Sharma | B5: Sales Exec | C5: DEL-01 | D5: P | E5: P | F5: P | G5: A | H5: P | I5: P | J5: P | K5: =COUNTIF(D5:J5,"P") | L5: =IF(COUNTA(D5:J5)=0,"",K5/COUNTA(D5:J5))
K6: =COUNTIF(D6:J6,"P") | L6: =IF(COUNTA(D6:J6)=0,"",K6/COUNTA(D6:J6))
K7: =COUNTIF(D7:J7,"P") | L7: =IF(COUNTA(D7:J7)=0,"",K7/COUNTA(D7:J7))
K8: =COUNTIF(D8:J8,"P") | L8: =IF(COUNTA(D8:J8)=0,"",K8/COUNTA(D8:J8))
K9: =COUNTIF(D9:J9,"P") | L9: =IF(COUNTA(D9:J9)=0,"",K9/COUNTA(D9:J9))
K10: =COUNTIF(D10:J10,"P") | L10: =IF(COUNTA(D10:J10)=0,"",K10/COUNTA(D10:J10))
K11: =COUNTIF(D11:J11,"P") | L11: =IF(COUNTA(D11:J11)=0,"",K11/COUNTA(D11:J11))
K12: =COUNTIF(D12:J12,"P") | L12: =IF(COUNTA(D12:J12)=0,"",K12/COUNTA(D12:J12))
K13: =COUNTIF(D13:J13,"P") | L13: =IF(COUNTA(D13:J13)=0,"",K13/COUNTA(D13:J13))
K14: =COUNTIF(D14:J14,"P") | L14: =IF(COUNTA(D14:J14)=0,"",K14/COUNTA(D14:J14))
K15: =COUNTIF(D15:J15,"P") | L15: =IF(COUNTA(D15:J15)=0,"",K15/COUNTA(D15:J15))
K16: =COUNTIF(D16:J16,"P") | L16: =IF(COUNTA(D16:J16)=0,"",K16/COUNTA(D16:J16))
K17: =COUNTIF(D17:J17,"P") | L17: =IF(COUNTA(D17:J17)=0,"",K17/COUNTA(D17:J17))
... K29: =COUNTIF(D29:J29,"P") | L29: =IF(COUNTA(D29:J29)=0,"",K29/COUNTA(D29:J29))

Sheet 8. Daily Sales Report
A1: Daily Sales Report
A2: One row per pop-up per day. Feeds the season sales roll-up at the bottom.
A4: Date | B4: City | C4: Pop-up ID | D4: Units Sold | E4: Gross Sales (₹) | F4: Discounts (₹) | G4: Net Sales (₹) | H4: Bills | I4: Avg Bill (₹) | J4: Reported By
A5: 2026-10-15 | B5: Delhi | C5: DEL-01 | D5: 42 | E5: 168000 | F5: 8000 | G5: =E5-F5 | H5: 38 | I5: =IF(H5=0,0,G5/H5) | J5: R. Verma
G6: =E6-F6 | I6: =IF(H6=0,0,G6/H6)
G7: =E7-F7 | I7: =IF(H7=0,0,G7/H7)
G8: =E8-F8 | I8: =IF(H8=0,0,G8/H8)
G9: =E9-F9 | I9: =IF(H9=0,0,G9/H9)
G10: =E10-F10 | I10: =IF(H10=0,0,G10/H10)
G11: =E11-F11 | I11: =IF(H11=0,0,G11/H11)
G12: =E12-F12 | I12: =IF(H12=0,0,G12/H12)
G13: =E13-F13 | I13: =IF(H13=0,0,G13/H13)
G14: =E14-F14 | I14: =IF(H14=0,0,G14/H14)
G15: =E15-F15 | I15: =IF(H15=0,0,G15/H15)
G16: =E16-F16 | I16: =IF(H16=0,0,G16/H16)
G17: =E17-F17 | I17: =IF(H17=0,0,G17/H17)
... G29: =E29-F29 | I29: =IF(H29=0,0,G29/H29)
A30: SEASON TOTAL | D30: =SUM(D5:D29) | E30: =SUM(E5:E29) | F30: =SUM(F5:F29) | G30: =SUM(G5:G29) | H30: =SUM(H5:H29) | I30: =IF(H30=0,0,G30/H30)

Sheet 9. Inventory & Replenish
A1: Inventory & Stock Replenishment
A2: SKU-level daily reconciliation per pop-up. Closing = Opening + Received − Sold − Damaged.
A4: Date | B4: Pop-up ID | C4: SKU / Product | D4: Opening | E4: Received | F4: Sold | G4: Damaged | H4: Closing | I4: Reorder Level | J4: Reorder?
A5: 2026-10-15 | B5: DEL-01 | C5: Rose Petal 200g | D5: 60 | E5: 24 | F5: 42 | G5: 0 | H5: =D5+E5-F5-G5 | I5: 20 | J5: =IF(H5<=I5,"REORDER","OK")
H6: =D6+E6-F6-G6 | J6: =IF(H6<=I6,"REORDER","OK")
H7: =D7+E7-F7-G7 | J7: =IF(H7<=I7,"REORDER","OK")
H8: =D8+E8-F8-G8 | J8: =IF(H8<=I8,"REORDER","OK")
H9: =D9+E9-F9-G9 | J9: =IF(H9<=I9,"REORDER","OK")
H10: =D10+E10-F10-G10 | J10: =IF(H10<=I10,"REORDER","OK")
H11: =D11+E11-F11-G11 | J11: =IF(H11<=I11,"REORDER","OK")
H12: =D12+E12-F12-G12 | J12: =IF(H12<=I12,"REORDER","OK")
H13: =D13+E13-F13-G13 | J13: =IF(H13<=I13,"REORDER","OK")
H14: =D14+E14-F14-G14 | J14: =IF(H14<=I14,"REORDER","OK")
H15: =D15+E15-F15-G15 | J15: =IF(H15<=I15,"REORDER","OK")
H16: =D16+E16-F16-G16 | J16: =IF(H16<=I16,"REORDER","OK")
H17: =D17+E17-F17-G17 | J17: =IF(H17<=I17,"REORDER","OK")
... H29: =D29+E29-F29-G29 | J29: =IF(H29<=I29,"REORDER","OK")

Sheet 10. Footfall & Conversion
A1: Footfall & Conversion
A2: Daily footfall vs bills. Conversion = Bills / Footfall.
A4: Date | B4: City | C4: Pop-up ID | D4: Footfall | E4: Walk-ins Engaged | F4: Bills | G4: Conversion % | H4: Reported By
A5: 2026-10-15 | B5: Delhi | C5: DEL-01 | D5: 520 | E5: 180 | F5: 38 | G5: =IF(D5=0,0,F5/D5) | H5: R. Verma
G6: =IF(D6=0,0,F6/D6)
G7: =IF(D7=0,0,F7/D7)
G8: =IF(D8=0,0,F8/D8)
G9: =IF(D9=0,0,F9/D9)
G10: =IF(D10=0,0,F10/D10)
G11: =IF(D11=0,0,F11/D11)
G12: =IF(D12=0,0,F12/D12)
G13: =IF(D13=0,0,F13/D13)
G14: =IF(D14=0,0,F14/D14)
G15: =IF(D15=0,0,F15/D15)
G16: =IF(D16=0,0,F16/D16)
G17: =IF(D17=0,0,F17/D17)
... G29: =IF(D29=0,0,F29/D29)

Sheet 11. Customer Feedback
A1: Customer Feedback Log
A2: Capture verbatim customer feedback and resolution. Feeds Doft brand & product insights.
A4: Date | B4: City | C4: Pop-up ID | D4: Customer | E4: Rating (1-5) | F4: Category | G4: Feedback | H4: Action Taken | I4: Status
A5: 2026-10-15 | B5: Delhi | C5: DEL-01 | D5: Walk-in | E5: 5 | F5: Fragrance | G5: Loved the sandalwood range | H5: Recommended gift set | I5: Closed

Sheet 12. Compliance Checklist
A1: Compliance & Legal Checklist
A2: Per pop-up. Status: Not Started / In Progress / Done / N/A.
A4: # | B4: Requirement | C4: Responsible | D4: Due (T-) | E4: Status | F4: Remarks
A5: 1 | B5: Mall space licence agreement signed
A6: 2 | B6: Shops & Establishment / trade compliance
A7: 3 | B7: GST registration & e-invoicing ready
A8: 4 | B8: Staff police / background verification (BGV) complete
A9: 5 | B9: PF & ESIC registration for deployed staff
A10: 6 | B10: Public liability / event insurance in place
A11: 7 | B11: Fire & safety and electrical clearance
A12: 8 | B12: Access passes & loading/unloading permits
A13: 9 | B13: Electricity connection / DG arrangement
A14: 10 | B14: POS/EDC machine received & tested
A15: 11 | B15: Uniforms received (returnable) & logged
A16: 12 | B16: Stock receipt & insurance-in-transit from Ghaziabad
... A19: 15 | B19: Dismantling & fixture-return sign-off plan

Sheet 13. Risk Register
A1: Risk Register
A2: Score = Likelihood × Impact (1-5 each). Mitigate high scores first.
A4: # | B4: Risk | C4: Likelihood (1-5) | D4: Impact (1-5) | E4: Score | F4: Mitigation | G4: Owner
A5: 1 | B5: Staff attrition after training | C5: 4 | D5: 4 | E5: =C5*D5 | F5: Maintain 15% trained bench; immediate no-cost replacement | G5: Ops Head
A6: 2 | B6: Mall licence / permission delay | C6: 3 | D6: 5 | E6: =C6*D6 | F6: Start licensing at T-7w; parallel mall shortlist | G6: Legal
A7: 3 | B7: Stock-out during peak days | C7: 3 | D7: 5 | E7: =C7*D7 | F7: Reorder levels + daily replenishment from 90 sq ft stockroom | G7: Logistics
A8: 4 | B8: POS/EDC downtime | C8: 2 | D8: 4 | E8: =C8*D8 | F8: Backup EDC + trained cashier; mall Wi-Fi + dongle failover | G8: Cashier/IT
A9: 5 | B9: Underperformance vs sales target | C9: 3 | D9: 4 | E9: =C9*D9 | F9: Daily reporting, incentives, TL coaching | G9: Team Leader
A10: 6 | B10: Kiosk fabrication delay | C10: 2 | D10: 5 | E10: =C10*D10 | F10: Vendor SLA + 3-day buffer before go-live | G10: Projects
A11: 7 | B11: Statutory non-compliance | C11: 2 | D11: 5 | E11: =C11*D11 | F11: Compliance checklist sign-off before go-live | G11: Legal
A12: 8 | B12: Cash handling / shrinkage | C12: 2 | D12: 4 | E12: =C12*D12 | F12: Dual control, daily reconciliation, CCTV where available | G12: Cashier/TL
A13: 9 | B13: Uniform damage / loss | C13: 2 | D13: 2 | E13: =C13*D13 | F13: Issue log, upkeep SOP, deposit control | G13: Team Leader
